bridgecrew/__init__.py
bridgecrew/banner.py
bridgecrew/main.py
bridgecrew/version.py
bridgecrew-3.2.500.data/scripts/bridgecrew
bridgecrew-3.2.500.data/scripts/bridgecrew.cmd
bridgecrew-3.2.500.dist-info/METADATA
bridgecrew-3.2.500.dist-info/WHEEL
bridgecrew-3.2.500.dist-info/top_level.txt
bridgecrew-3.2.500.dist-info/RECORD
