Metadata-Version: 2.1
Name: bridgecrew
Version: 3.2.500
Summary: Infrastructure as code static analysis
Home-page: https://github.com/bridgecrewio/bridgecrew
Author: bridgecrew
Author-email: meet@bridgecrew.io
License: Apache License 2.0
Platform: UNKNOWN
Classifier: Environment :: Console
Classifier: Intended Audience :: Developers
Classifier: Intended Audience :: System Administrators
Classifier: License :: OSI Approved :: Apache Software License
Classifier: Programming Language :: Python :: 3 :: Only
Classifier: Programming Language :: Python :: 3.7
Classifier: Programming Language :: Python :: 3.8
Classifier: Programming Language :: Python :: 3.9
Classifier: Programming Language :: Python :: 3.10
Classifier: Programming Language :: Python :: 3.11
Classifier: Topic :: Security
Classifier: Topic :: Software Development :: Build Tools
Requires-Dist: checkov ==3.2.500
